micro_sip_nextcloud_bridge-0.1.1.dist-info/METADATA
micro_sip_nextcloud_bridge-0.1.1.dist-info/WHEEL
micro_sip_nextcloud_bridge-0.1.1.dist-info/entry_points.txt
micro_sip_nextcloud_bridge-0.1.1.dist-info/licenses/LICENSE
micro_sip_nextcloud_bridge/__init__.py
micro_sip_nextcloud_bridge/__main__.py
micro_sip_nextcloud_bridge/img/microsip.ico
micro_sip_nextcloud_bridge/logger.py
micro_sip_nextcloud_bridge/settings.py
micro_sip_nextcloud_bridge-0.1.1.dist-info/RECORD
