Metadata-Version: 2.1
Name: micro-sip-nextcloud-bridge
Version: 0.1.1
Summary: A Bridge between MicroSip and Nextcloud.
Author-Email: Julius Koenig <info@bastelquartier.de>
License:                     GNU GENERAL PUBLIC LICENSE
Project-URL: homepage, https://github.com/JuliusKoenig/micro-sip-nextcloud-bridge
Requires-Python: >=3.12
Requires-Dist: wiederverwendbar[uvicorn]>=0.7.3
Requires-Dist: fastapi>=0.115.9
Requires-Dist: requests>=2.32.3
Requires-Dist: vobject>=0.9.9
